xdatbus/__init__.py
xdatbus/c01_xdc_aggregate.py
xdatbus/c02a_xdc_unwrap.py
xdatbus/c02b_xyz_unwarp.py
xdatbus/c03_thermal_report.py
xdatbus/c04_xml2xyz.py
xdatbus/c05_sum_hills.py
xdatbus/fcli.py
xdatbus/fun_bld.py
xdatbus/fun_com.py
xdatbus/fun_mtd.py
xdatbus/resources/__init__.py
xdatbus/resources/sum_hills.sh
xdatbus/resources/vis_data.yaml
xdatbus/utils.py
xdatbus/utils_bpy.py
xdatbus-0.3.8.dist-info/LICENSE
xdatbus-0.3.8.dist-info/METADATA
xdatbus-0.3.8.dist-info/WHEEL
xdatbus-0.3.8.dist-info/entry_points.txt
xdatbus-0.3.8.dist-info/RECORD
