Metadata-Version: 2.1
Name: xdatbus
Version: 0.3.8
Summary: A Python package enhancing VASP AIMD simulation
Home-page: https://xdatbus.readthedocs.io/en/latest/
License: MIT
Keywords: python,aimd,vasp,xdatcar
Author: Jiacheng Wang
Author-email: jiachengwang@umass.edu
Maintainer: Jiacheng Wang
Requires-Python: >=3.10,<3.13
Classifier: Development Status :: 1 - Planning
Classifier: Intended Audience :: Science/Research
Classifier: License :: OSI Approved :: MIT License
Classifier: Operating System :: OS Independent
Classifier: Programming Language :: Python :: 3
Classifier: Programming Language :: Python :: 3.10
Classifier: Programming Language :: Python :: 3.11
Classifier: Programming Language :: Python :: 3.12
Provides-Extra: dash
Provides-Extra: meta
Requires-Dist: ase (>=3.23.0,<4.0.0)
Requires-Dist: bpy (==4.3.0) ; (python_version == "3.11.*") and (extra == "meta")
Requires-Dist: dash (==2.18.2) ; extra == "dash"
Requires-Dist: mdanalysis (>=2.7.0,<3.0.0)
Requires-Dist: numpy
Requires-Dist: ovito ; extra == "meta"
Requires-Dist: pandas
Requires-Dist: plotly (==6.0.0) ; extra == "dash"
Requires-Dist: pyarrow
Requires-Dist: pymatgen (>=2025.1.0,<2026.0.0)
Requires-Dist: pyyaml (==6.0.2) ; extra == "meta"
Requires-Dist: rdkit (==2024.9.5) ; extra == "meta"
Requires-Dist: rich
Requires-Dist: statsmodels
Project-URL: Documentation, https://xdatbus.readthedocs.io/en/latest/
Project-URL: Repository, https://github.com/jcwang587/xdatbus/
